redfishLiteApi.py
redfishliteapi-1.2.0.dist-info/METADATA
redfishliteapi-1.2.0.dist-info/WHEEL
redfishliteapi-1.2.0.dist-info/entry_points.txt
redfishliteapi-1.2.0.dist-info/top_level.txt
redfishliteapi-1.2.0.dist-info/RECORD
