Metadata-Version: 2.4
Name: redfishLiteApi
Version: 1.2.0
Summary: A lightweight Redfish API command-line tool
Home-page: https://github.com/jeffery12240122/redfishLiteAPI
Author: Jeffery Lin
Author-email: jeffery12240122@gmail.com
Classifier: Programming Language :: Python :: 3
Classifier: Operating System :: OS Independent
Classifier: Environment :: Console
Classifier: License :: OSI Approved :: MIT License
Requires-Python: >=3.6
Requires-Dist: requests>=2.25.1
Dynamic: author
Dynamic: author-email
Dynamic: classifier
Dynamic: description
Dynamic: description-content-type
Dynamic: home-page
Dynamic: requires-dist
Dynamic: requires-python
Dynamic: summary
